calculator
tests
