Metadata-Version: 1.1
Name: basic-calculator-101
Version: 1.3
Summary: Calculator with basic functions: Add, Subtract, Multiply, Divide, Nth-root, ability to reset to 0
Home-page: https://github.com/Ifyokoh/calculator
Author: Ifeoma Okoh
Author-email: odibest1893@gmail.com
License: MIT
Keywords: calculator
Platform: UNKNOWN
Classifier: Intended Audience :: Education
Classifier: License :: OSI Approved :: MIT License
Classifier: Programming Language :: Python :: 3
